scrules/ScRules.py
scrules/__init__.py
scrules/data/__init__.py
scrules/utils/DataLoader.py
scrules/utils/RegNet.py
scrules/utils/__init__.py
scrules/utils/draw.py
scrules/utils/eval_calculate.py
scrules/utils/merge_sc_transactions_data.py
scrules/utils/net.py
scrules/utils/rules_csv2sql.py
scrules-1.0.7.dist-info/LICENSE
scrules-1.0.7.dist-info/METADATA
scrules-1.0.7.dist-info/WHEEL
scrules-1.0.7.dist-info/top_level.txt
scrules-1.0.7.dist-info/RECORD
